aett/mongodbasync/__init__.py
aett/mongodbasync/async_commit_store.py
aett/mongodbasync/async_persistence_management.py
aett/mongodbasync/async_snapshot_store.py
aett/mongodbasync/mapping.py
aett_mongodb_async-2.1.0.dist-info/LICENSE
aett_mongodb_async-2.1.0.dist-info/METADATA
aett_mongodb_async-2.1.0.dist-info/WHEEL
aett_mongodb_async-2.1.0.dist-info/top_level.txt
aett_mongodb_async-2.1.0.dist-info/RECORD
