Metadata-Version: 2.1
Name: aett-mongodb-async
Version: 2.1.0
Summary: MongoDB connector for aett event store
Author-email: Jacob Reimers <pypi@reimers.io>
License: MIT License
Project-URL: Homepage, https://github.com/jjrdk/aett
Keywords: events,event store,mongo,mongodb
Classifier: License :: OSI Approved :: MIT License
Classifier: Programming Language :: Python
Classifier: Programming Language :: Python :: 3
Requires-Python: >=3.10
License-File: LICENSE
Requires-Dist: aett-domain>=2.1.0
Requires-Dist: pymongo~=4.8.0
Provides-Extra: dev
Requires-Dist: pip-tools; extra == "dev"
Requires-Dist: pytest; extra == "dev"
Requires-Dist: behave; extra == "dev"
